authbase/__init__.py
authbase-1.0.20.dist-info/METADATA
authbase-1.0.20.dist-info/WHEEL
authbase-1.0.20.dist-info/licenses/LICENSE
authbase-1.0.20.dist-info/RECORD
